pepaln/__init__.py
pepaln/__main__.py
pepaln/align.py
pepaln/parse.py
pepaln/render.py
pepaln-1.0.0.dist-info/LICENSE
pepaln-1.0.0.dist-info/METADATA
pepaln-1.0.0.dist-info/WHEEL
pepaln-1.0.0.dist-info/top_level.txt
pepaln-1.0.0.dist-info/RECORD
