Metadata-Version: 2.1
Name: pepaln
Version: 1.0.0
Summary: Peptide Matcher 
Home-page: UNKNOWN
Author: Istvan Albert
Author-email: istvan.albert@gmail.com
License: UNKNOWN
Platform: UNKNOWN
Classifier: Programming Language :: Python :: 3
Classifier: License :: OSI Approved :: MIT License
Classifier: Operating System :: OS Independent
Requires-Python: >=3.6
License-File: LICENSE
Requires-Dist: plac (>=1.3)
Requires-Dist: intervaltree
Requires-Dist: FPDF
